digikey/__init__.py
digikey/constants.py
digikey/decorators.py
digikey/exceptions.py
digikey/utils.py
digikey/oauth/__init__.py
digikey/oauth/oauth2.py
digikey/v2/__init__.py
digikey/v2/api.py
digikey/v2/client.py
digikey/v2/directives.py
digikey/v2/models.py
digikey/v3/__init__.py
digikey/v3/api.py
digikey/v3/batchproductdetails/__init__.py
digikey/v3/batchproductdetails/api_client.py
digikey/v3/batchproductdetails/configuration.py
digikey/v3/batchproductdetails/rest.py
digikey/v3/batchproductdetails/api/__init__.py
digikey/v3/batchproductdetails/api/batch_search_api.py
digikey/v3/batchproductdetails/models/__init__.py
digikey/v3/batchproductdetails/models/api_error_response.py
digikey/v3/batchproductdetails/models/api_validation_error.py
digikey/v3/batchproductdetails/models/associated_product.py
digikey/v3/batchproductdetails/models/basic_product.py
digikey/v3/batchproductdetails/models/batch_product_details_request.py
digikey/v3/batchproductdetails/models/batch_product_details_response.py
digikey/v3/batchproductdetails/models/iso_search_locale.py
digikey/v3/batchproductdetails/models/kit_part.py
digikey/v3/batchproductdetails/models/limited_taxonomy.py
digikey/v3/batchproductdetails/models/media_links.py
digikey/v3/batchproductdetails/models/pid_vid.py
digikey/v3/batchproductdetails/models/price_break.py
digikey/v3/batchproductdetails/models/product_details.py
digikey/v3/ordersupport/__init__.py
digikey/v3/ordersupport/api_client.py
digikey/v3/ordersupport/configuration.py
digikey/v3/ordersupport/rest.py
digikey/v3/ordersupport/api/__init__.py
digikey/v3/ordersupport/api/order_details_api.py
digikey/v3/ordersupport/models/__init__.py
digikey/v3/ordersupport/models/address.py
digikey/v3/ordersupport/models/api_error_response.py
digikey/v3/ordersupport/models/api_validation_error.py
digikey/v3/ordersupport/models/back_order_details.py
digikey/v3/ordersupport/models/default_shipping.py
digikey/v3/ordersupport/models/line_item.py
digikey_api-1.1.0.dist-info/LICENSE
digikey_api-1.1.0.dist-info/METADATA
digikey_api-1.1.0.dist-info/WHEEL
digikey_api-1.1.0.dist-info/top_level.txt
digikey_api-1.1.0.dist-info/RECORD
