Metadata-Version: 2.1
Name: digikey-api
Version: 1.1.0
Summary: Python client for Digikey API
Home-page: https://github.com/peeter123/digikey-api
Author: Peter Oostewechel
Author-email: peter_oostewechel@hotmail.com
License: GPL v3
Classifier: Development Status :: 3 - Alpha
Classifier: Environment :: Web Environment
Classifier: Intended Audience :: Developers
Classifier: License :: OSI Approved :: GNU General Public License v3 (GPLv3)
Classifier: Programming Language :: Python :: 3.6
Classifier: Topic :: Software Development
License-File: LICENSE
Requires-Dist: requests>=2.22.0
Requires-Dist: retrying>=1.3.3
Requires-Dist: inflection>=0.3.1
Requires-Dist: certauth>=1.3.0
Requires-Dist: urllib3>=1.25.3
